{
    "@context": "http://iiif.io/api/discovery/1/context.json",
    "id": "https://utkdigitalinitiatives.github.io/change_discovery/activity/page-445.json",
    "type": "OrderedCollectionPage",
    "partOf": {
        "id": "https://utkdigitalinitiatives.github.io/change_discovery/activity/all-changes.json",
        "type": "OrderedCollection"
    },
    "prev": {
        "id": "https://utkdigitalinitiatives.github.io/change_discovery/activity/page-444.json",
        "type": "OrderedCollectionPage"
    },
    "next": {
        "id": "https://utkdigitalinitiatives.github.io/change_discovery/activity/page-446.json",
        "type": "OrderedCollectionPage"
    },
    "orderedItems": [
        {
            "type": "Update",
            "object": {
                "id": "https://digital.lib.utk.edu/assemble/manifest/utsmc/17450",
                "type": "Manifest"
            }
        },
        {
            "type": "Update",
            "object": {
                "id": "https://digital.lib.utk.edu/assemble/manifest/utsmc/17471",
                "type": "Manifest"
            }
        },
        {
            "type": "Update",
            "object": {
                "id": "https://digital.lib.utk.edu/assemble/manifest/utsmc/17476",
                "type": "Manifest"
            }
        },
        {
            "type": "Update",
            "object": {
                "id": "https://digital.lib.utk.edu/assemble/manifest/utsmc/17483",
                "type": "Manifest"
            }
        },
        {
            "type": "Update",
            "object": {
                "id": "https://digital.lib.utk.edu/assemble/manifest/utsmc/17490",
                "type": "Manifest"
            }
        },
        {
            "type": "Update",
            "object": {
                "id": "https://digital.lib.utk.edu/assemble/manifest/volvoices/4125",
                "type": "Manifest"
            }
        },
        {
            "type": "Update",
            "object": {
                "id": "https://digital.lib.utk.edu/assemble/manifest/volvoices/4130",
                "type": "Manifest"
            }
        },
        {
            "type": "Update",
            "object": {
                "id": "https://digital.lib.utk.edu/assemble/manifest/volvoices/4133",
                "type": "Manifest"
            }
        },
        {
            "type": "Update",
            "object": {
                "id": "https://digital.lib.utk.edu/assemble/manifest/volvoices/4137",
                "type": "Manifest"
            }
        },
        {
            "type": "Update",
            "object": {
                "id": "https://digital.lib.utk.edu/assemble/manifest/volvoices/4142",
                "type": "Manifest"
            }
        },
        {
            "type": "Update",
            "object": {
                "id": "https://digital.lib.utk.edu/assemble/manifest/volvoices/4145",
                "type": "Manifest"
            }
        },
        {
            "type": "Update",
            "object": {
                "id": "https://digital.lib.utk.edu/assemble/manifest/volvoices/4169",
                "type": "Manifest"
            }
        },
        {
            "type": "Update",
            "object": {
                "id": "https://digital.lib.utk.edu/assemble/manifest/volvoices/4172",
                "type": "Manifest"
            }
        },
        {
            "type": "Update",
            "object": {
                "id": "https://digital.lib.utk.edu/assemble/manifest/volvoices/4174",
                "type": "Manifest"
            }
        },
        {
            "type": "Update",
            "object": {
                "id": "https://digital.lib.utk.edu/assemble/manifest/volvoices/4177",
                "type": "Manifest"
            }
        },
        {
            "type": "Update",
            "object": {
                "id": "https://digital.lib.utk.edu/assemble/manifest/volvoices/4182",
                "type": "Manifest"
            }
        },
        {
            "type": "Update",
            "object": {
                "id": "https://digital.lib.utk.edu/assemble/manifest/volvoices/4187",
                "type": "Manifest"
            }
        },
        {
            "type": "Update",
            "object": {
                "id": "https://digital.lib.utk.edu/assemble/manifest/volvoices/4190",
                "type": "Manifest"
            }
        },
        {
            "type": "Update",
            "object": {
                "id": "https://digital.lib.utk.edu/assemble/manifest/volvoices/4195",
                "type": "Manifest"
            }
        },
        {
            "type": "Update",
            "object": {
                "id": "https://digital.lib.utk.edu/assemble/manifest/volvoices/4197",
                "type": "Manifest"
            }
        },
        {
            "type": "Update",
            "object": {
                "id": "https://digital.lib.utk.edu/assemble/manifest/volvoices/4199",
                "type": "Manifest"
            }
        },
        {
            "type": "Update",
            "object": {
                "id": "https://digital.lib.utk.edu/assemble/manifest/volvoices/4202",
                "type": "Manifest"
            }
        },
        {
            "type": "Update",
            "object": {
                "id": "https://digital.lib.utk.edu/assemble/manifest/volvoices/4205",
                "type": "Manifest"
            }
        },
        {
            "type": "Update",
            "object": {
                "id": "https://digital.lib.utk.edu/assemble/manifest/volvoices/4210",
                "type": "Manifest"
            }
        },
        {
            "type": "Update",
            "object": {
                "id": "https://digital.lib.utk.edu/assemble/manifest/volvoices/4215",
                "type": "Manifest"
            }
        },
        {
            "type": "Update",
            "object": {
                "id": "https://digital.lib.utk.edu/assemble/manifest/volvoices/4218",
                "type": "Manifest"
            }
        },
        {
            "type": "Update",
            "object": {
                "id": "https://digital.lib.utk.edu/assemble/manifest/volvoices/4222",
                "type": "Manifest"
            }
        },
        {
            "type": "Update",
            "object": {
                "id": "https://digital.lib.utk.edu/assemble/manifest/volvoices/4225",
                "type": "Manifest"
            }
        },
        {
            "type": "Update",
            "object": {
                "id": "https://digital.lib.utk.edu/assemble/manifest/volvoices/4230",
                "type": "Manifest"
            }
        },
        {
            "type": "Update",
            "object": {
                "id": "https://digital.lib.utk.edu/assemble/manifest/volvoices/4232",
                "type": "Manifest"
            }
        },
        {
            "type": "Update",
            "object": {
                "id": "https://digital.lib.utk.edu/assemble/manifest/volvoices/4235",
                "type": "Manifest"
            }
        },
        {
            "type": "Update",
            "object": {
                "id": "https://digital.lib.utk.edu/assemble/manifest/volvoices/4240",
                "type": "Manifest"
            }
        },
        {
            "type": "Update",
            "object": {
                "id": "https://digital.lib.utk.edu/assemble/manifest/volvoices/4245",
                "type": "Manifest"
            }
        },
        {
            "type": "Update",
            "object": {
                "id": "https://digital.lib.utk.edu/assemble/manifest/volvoices/4248",
                "type": "Manifest"
            }
        },
        {
            "type": "Update",
            "object": {
                "id": "https://digital.lib.utk.edu/assemble/manifest/volvoices/4253",
                "type": "Manifest"
            }
        },
        {
            "type": "Update",
            "object": {
                "id": "https://digital.lib.utk.edu/assemble/manifest/volvoices/4258",
                "type": "Manifest"
            }
        },
        {
            "type": "Update",
            "object": {
                "id": "https://digital.lib.utk.edu/assemble/manifest/volvoices/4263",
                "type": "Manifest"
            }
        },
        {
            "type": "Update",
            "object": {
                "id": "https://digital.lib.utk.edu/assemble/manifest/volvoices/4265",
                "type": "Manifest"
            }
        },
        {
            "type": "Update",
            "object": {
                "id": "https://digital.lib.utk.edu/assemble/manifest/volvoices/4270",
                "type": "Manifest"
            }
        },
        {
            "type": "Update",
            "object": {
                "id": "https://digital.lib.utk.edu/assemble/manifest/volvoices/4273",
                "type": "Manifest"
            }
        },
        {
            "type": "Update",
            "object": {
                "id": "https://digital.lib.utk.edu/assemble/manifest/volvoices/4278",
                "type": "Manifest"
            }
        },
        {
            "type": "Update",
            "object": {
                "id": "https://digital.lib.utk.edu/assemble/manifest/volvoices/4281",
                "type": "Manifest"
            }
        },
        {
            "type": "Update",
            "object": {
                "id": "https://digital.lib.utk.edu/assemble/manifest/volvoices/4285",
                "type": "Manifest"
            }
        },
        {
            "type": "Update",
            "object": {
                "id": "https://digital.lib.utk.edu/assemble/manifest/volvoices/4291",
                "type": "Manifest"
            }
        },
        {
            "type": "Update",
            "object": {
                "id": "https://digital.lib.utk.edu/assemble/manifest/volvoices/4295",
                "type": "Manifest"
            }
        },
        {
            "type": "Update",
            "object": {
                "id": "https://digital.lib.utk.edu/assemble/manifest/volvoices/4300",
                "type": "Manifest"
            }
        },
        {
            "type": "Update",
            "object": {
                "id": "https://digital.lib.utk.edu/assemble/manifest/volvoices/4303",
                "type": "Manifest"
            }
        },
        {
            "type": "Update",
            "object": {
                "id": "https://digital.lib.utk.edu/assemble/manifest/volvoices/4310",
                "type": "Manifest"
            }
        },
        {
            "type": "Update",
            "object": {
                "id": "https://digital.lib.utk.edu/assemble/manifest/volvoices/4313",
                "type": "Manifest"
            }
        },
        {
            "type": "Update",
            "object": {
                "id": "https://digital.lib.utk.edu/assemble/manifest/volvoices/4316",
                "type": "Manifest"
            }
        },
        {
            "type": "Update",
            "object": {
                "id": "https://digital.lib.utk.edu/assemble/manifest/volvoices/4318",
                "type": "Manifest"
            }
        },
        {
            "type": "Update",
            "object": {
                "id": "https://digital.lib.utk.edu/assemble/manifest/volvoices/4323",
                "type": "Manifest"
            }
        },
        {
            "type": "Update",
            "object": {
                "id": "https://digital.lib.utk.edu/assemble/manifest/volvoices/4327",
                "type": "Manifest"
            }
        },
        {
            "type": "Update",
            "object": {
                "id": "https://digital.lib.utk.edu/assemble/manifest/volvoices/4331",
                "type": "Manifest"
            }
        },
        {
            "type": "Update",
            "object": {
                "id": "https://digital.lib.utk.edu/assemble/manifest/volvoices/4334",
                "type": "Manifest"
            }
        },
        {
            "type": "Update",
            "object": {
                "id": "https://digital.lib.utk.edu/assemble/manifest/volvoices/4337",
                "type": "Manifest"
            }
        },
        {
            "type": "Update",
            "object": {
                "id": "https://digital.lib.utk.edu/assemble/manifest/volvoices/4342",
                "type": "Manifest"
            }
        },
        {
            "type": "Update",
            "object": {
                "id": "https://digital.lib.utk.edu/assemble/manifest/volvoices/4345",
                "type": "Manifest"
            }
        },
        {
            "type": "Update",
            "object": {
                "id": "https://digital.lib.utk.edu/assemble/manifest/volvoices/4349",
                "type": "Manifest"
            }
        },
        {
            "type": "Update",
            "object": {
                "id": "https://digital.lib.utk.edu/assemble/manifest/volvoices/4353",
                "type": "Manifest"
            }
        },
        {
            "type": "Update",
            "object": {
                "id": "https://digital.lib.utk.edu/assemble/manifest/volvoices/4358",
                "type": "Manifest"
            }
        },
        {
            "type": "Update",
            "object": {
                "id": "https://digital.lib.utk.edu/assemble/manifest/volvoices/4361",
                "type": "Manifest"
            }
        },
        {
            "type": "Update",
            "object": {
                "id": "https://digital.lib.utk.edu/assemble/manifest/volvoices/4364",
                "type": "Manifest"
            }
        },
        {
            "type": "Update",
            "object": {
                "id": "https://digital.lib.utk.edu/assemble/manifest/volvoices/4369",
                "type": "Manifest"
            }
        },
        {
            "type": "Update",
            "object": {
                "id": "https://digital.lib.utk.edu/assemble/manifest/volvoices/4374",
                "type": "Manifest"
            }
        },
        {
            "type": "Update",
            "object": {
                "id": "https://digital.lib.utk.edu/assemble/manifest/volvoices/4379",
                "type": "Manifest"
            }
        },
        {
            "type": "Update",
            "object": {
                "id": "https://digital.lib.utk.edu/assemble/manifest/volvoices/4383",
                "type": "Manifest"
            }
        },
        {
            "type": "Update",
            "object": {
                "id": "https://digital.lib.utk.edu/assemble/manifest/volvoices/4386",
                "type": "Manifest"
            }
        },
        {
            "type": "Update",
            "object": {
                "id": "https://digital.lib.utk.edu/assemble/manifest/volvoices/4391",
                "type": "Manifest"
            }
        },
        {
            "type": "Update",
            "object": {
                "id": "https://digital.lib.utk.edu/assemble/manifest/volvoices/4397",
                "type": "Manifest"
            }
        },
        {
            "type": "Update",
            "object": {
                "id": "https://digital.lib.utk.edu/assemble/manifest/volvoices/4400",
                "type": "Manifest"
            }
        },
        {
            "type": "Update",
            "object": {
                "id": "https://digital.lib.utk.edu/assemble/manifest/volvoices/4403",
                "type": "Manifest"
            }
        },
        {
            "type": "Update",
            "object": {
                "id": "https://digital.lib.utk.edu/assemble/manifest/volvoices/4408",
                "type": "Manifest"
            }
        },
        {
            "type": "Update",
            "object": {
                "id": "https://digital.lib.utk.edu/assemble/manifest/volvoices/4412",
                "type": "Manifest"
            }
        },
        {
            "type": "Update",
            "object": {
                "id": "https://digital.lib.utk.edu/assemble/manifest/volvoices/4417",
                "type": "Manifest"
            }
        },
        {
            "type": "Update",
            "object": {
                "id": "https://digital.lib.utk.edu/assemble/manifest/volvoices/4421",
                "type": "Manifest"
            }
        },
        {
            "type": "Update",
            "object": {
                "id": "https://digital.lib.utk.edu/assemble/manifest/volvoices/4423",
                "type": "Manifest"
            }
        },
        {
            "type": "Update",
            "object": {
                "id": "https://digital.lib.utk.edu/assemble/manifest/volvoices/4427",
                "type": "Manifest"
            }
        },
        {
            "type": "Update",
            "object": {
                "id": "https://digital.lib.utk.edu/assemble/manifest/volvoices/4430",
                "type": "Manifest"
            }
        },
        {
            "type": "Update",
            "object": {
                "id": "https://digital.lib.utk.edu/assemble/manifest/volvoices/4432",
                "type": "Manifest"
            }
        },
        {
            "type": "Update",
            "object": {
                "id": "https://digital.lib.utk.edu/assemble/manifest/volvoices/4436",
                "type": "Manifest"
            }
        },
        {
            "type": "Update",
            "object": {
                "id": "https://digital.lib.utk.edu/assemble/manifest/volvoices/4441",
                "type": "Manifest"
            }
        },
        {
            "type": "Update",
            "object": {
                "id": "https://digital.lib.utk.edu/assemble/manifest/volvoices/4445",
                "type": "Manifest"
            }
        },
        {
            "type": "Update",
            "object": {
                "id": "https://digital.lib.utk.edu/assemble/manifest/volvoices/4448",
                "type": "Manifest"
            }
        },
        {
            "type": "Update",
            "object": {
                "id": "https://digital.lib.utk.edu/assemble/manifest/volvoices/4453",
                "type": "Manifest"
            }
        },
        {
            "type": "Update",
            "object": {
                "id": "https://digital.lib.utk.edu/assemble/manifest/volvoices/4456",
                "type": "Manifest"
            }
        },
        {
            "type": "Update",
            "object": {
                "id": "https://digital.lib.utk.edu/assemble/manifest/volvoices/4461",
                "type": "Manifest"
            }
        },
        {
            "type": "Update",
            "object": {
                "id": "https://digital.lib.utk.edu/assemble/manifest/volvoices/4464",
                "type": "Manifest"
            }
        },
        {
            "type": "Update",
            "object": {
                "id": "https://digital.lib.utk.edu/assemble/manifest/volvoices/4467",
                "type": "Manifest"
            }
        },
        {
            "type": "Update",
            "object": {
                "id": "https://digital.lib.utk.edu/assemble/manifest/volvoices/4470",
                "type": "Manifest"
            }
        },
        {
            "type": "Update",
            "object": {
                "id": "https://digital.lib.utk.edu/assemble/manifest/volvoices/4473",
                "type": "Manifest"
            }
        },
        {
            "type": "Update",
            "object": {
                "id": "https://digital.lib.utk.edu/assemble/manifest/volvoices/4476",
                "type": "Manifest"
            }
        },
        {
            "type": "Update",
            "object": {
                "id": "https://digital.lib.utk.edu/assemble/manifest/volvoices/4480",
                "type": "Manifest"
            }
        },
        {
            "type": "Update",
            "object": {
                "id": "https://digital.lib.utk.edu/assemble/manifest/volvoices/4484",
                "type": "Manifest"
            }
        },
        {
            "type": "Update",
            "object": {
                "id": "https://digital.lib.utk.edu/assemble/manifest/volvoices/4487",
                "type": "Manifest"
            }
        },
        {
            "type": "Update",
            "object": {
                "id": "https://digital.lib.utk.edu/assemble/manifest/volvoices/4490",
                "type": "Manifest"
            }
        },
        {
            "type": "Update",
            "object": {
                "id": "https://digital.lib.utk.edu/assemble/manifest/volvoices/4495",
                "type": "Manifest"
            }
        },
        {
            "type": "Update",
            "object": {
                "id": "https://digital.lib.utk.edu/assemble/manifest/volvoices/4499",
                "type": "Manifest"
            }
        },
        {
            "type": "Update",
            "object": {
                "id": "https://digital.lib.utk.edu/assemble/manifest/volvoices/4504",
                "type": "Manifest"
            }
        },
        {
            "type": "Update",
            "object": {
                "id": "https://digital.lib.utk.edu/assemble/manifest/volvoices/4514",
                "type": "Manifest"
            }
        }
    ]
}